informclient/__init__.py
informclient/informclient.py
informclient/api/request/__init__.py
informclient/api/request/request_validator.py
informclient/utils/__init__.py
informclient/utils/api_description.py
moe_inform_client-0.0.2.dist-info/LICENSE
moe_inform_client-0.0.2.dist-info/METADATA
moe_inform_client-0.0.2.dist-info/WHEEL
moe_inform_client-0.0.2.dist-info/top_level.txt
moe_inform_client-0.0.2.dist-info/RECORD
