Metadata-Version: 2.1
Name: moe-inform-client
Version: 0.0.2
Summary: This Python Package helps you in sending notifications through MoEngage Inform
Home-page: https://github.com/moengage/inform-client-python
Author: MoEngage
Author-email: inform@moengage.com
Project-URL: Bug Tracker, https://github.com/moengage/inform-client-python/issues
Keywords: MoEngage,Inform,MoEngage Inform,Customer Engagement,Transactional Alerts
Classifier: Development Status :: 5 - Production/Stable
Classifier: Intended Audience :: Developers
Classifier: License :: OSI Approved :: MIT License
Classifier: Operating System :: OS Independent
Classifier: Programming Language :: Python :: 3
Requires-Python: >=3.9
License-File: LICENSE
Requires-Dist: StrEnum (~=0.4.9)
Requires-Dist: urllib3 (~=1.26.5)
Requires-Dist: jsonschema (~=4.17.3)
